_raw.abi3.so
libraw_cffi-0.19.0.dist-info/RECORD
libraw_cffi-0.19.0.dist-info/METADATA
libraw_cffi-0.19.0.dist-info/COPYING
libraw_cffi-0.19.0.dist-info/top_level.txt
libraw_cffi-0.19.0.dist-info/WHEEL
libraw_cffi.libs/libgomp-f7e03b3e.so.1.0.0
libraw_cffi.libs/libraw-bf2953a8.so.20.0.0
libraw_cffi/_build.py
libraw_cffi/__init__.py
libraw_cffi/_api.py
libraw_cffi/tests/test_samples.py
libraw_cffi/tests/test_api.py
libraw_cffi/tests/__init__.py
libraw_cffi/tests/test_overview.py
