Metadata-Version: 1.2
Name: libraw-cffi
Version: 0.19.0
Summary: CFFI bindings for LibRaw
Home-page: https://github.com/Julian/libraw-cffi
Author: Julian Berman
Author-email: Julian+libraw_cffi@GrayVines.com
License: UNKNOWN
Project-URL: Source, https://github.com/Julian/libraw-cffi
Project-URL: Issues, https://github.com/Julian/libraw-cffi/issues/
Platform: UNKNOWN
Classifier: Development Status :: 3 - Alpha
Classifier: Operating System :: OS Independent
Classifier: Programming Language :: Python
Classifier: License :: OSI Approved :: MIT License
Classifier: Programming Language :: Python :: 3.6
Classifier: Programming Language :: Python :: 3.7
Classifier: Programming Language :: Python :: 3.8
Classifier: Programming Language :: Python :: 3
Classifier: Programming Language :: Python :: Implementation :: CPython
Classifier: Programming Language :: Python :: Implementation :: PyPy
